tdcca/__init__.py
tdcca/admm_computation.py
tdcca/data_preprocess.py
tdcca/multi_sim_val.py
tdcca/tcca_config.py
tdcca/val_computation.py
tdcca-0.0.0.dist-info/METADATA
tdcca-0.0.0.dist-info/RECORD
tdcca-0.0.0.dist-info/WHEEL
tdcca-0.0.0.dist-info/top_level.txt
