Metadata-Version: 2.1
Name: tdcca
Version: 0.0.0
Summary: Time-dependent Canonical Correlation Analysis
Home-page: https://github.com/xuefeicao/tdcca
Author: Xuefei Cao, Jun Ke, Xi Luo, Bjorn Sandstede
License: UNKNOWN
Platform: UNKNOWN
Requires-Dist: matplotlib (>=1.5.3)
Requires-Dist: numpy (>=1.11.1)
Requires-Dist: scipy (>=0.19.0)
Requires-Dist: six (>=1.10.0)
Requires-Dist: scikit-learn (>=0.18.1)
Requires-Dist: prox-tv (>=3.2.1)
Requires-Dist: pathos (>=0.2.2)
